{"officeTimings":{"officeInTime":"9:00","officeOutTime":"18:00","lunchBegin":"13:00","lunchEnd":"13:30","workingHours":9.0},"holidaysList":[],"selectedDate":"Dec 31, 2015 12:00:00 AM","subordinatesMainSwipes":{"70008":[{"userId":"70008","date":"Dec 31, 2015 12:00:00 AM","inTime":"Dec 31, 2015 1:15:29 PM","outTime":"Dec 31, 2015 6:20:43 PM","swipeEffectiveHours":1.8314787E7,"type":"PR"}],"60128":[{"userId":"60128","date":"Dec 31, 2015 12:00:00 AM","inTime":"Dec 31, 2015 9:23:38 AM","outTime":"Dec 31, 2015 12:55:59 PM","swipeEffectiveHours":1.2741E7,"type":"PR"},{"userId":"60128","date":"Dec 31, 2015 12:00:00 AM","inTime":"Dec 31, 2015 1:11:36 PM","outTime":"Dec 31, 2015 1:28:27 PM","swipeEffectiveHours":1011000.0,"type":"PR"}],"70014":[],"91780":[{"userId":"91780","date":"Dec 31, 2015 12:00:00 AM","inTime":"Dec 31, 2015 8:08:59 AM","outTime":"Dec 31, 2015 1:08:41 PM","swipeEffectiveHours":1.7982E7,"type":"PR"},{"userId":"91780","date":"Dec 31, 2015 12:00:00 AM","inTime":"Dec 31, 2015 1:26:23 PM","outTime":"Dec 31, 2015 6:20:44 PM","swipeEffectiveHours":1.7661566E7,"type":"PR"}],"50046":[{"userId":"50046","date":"Dec 31, 2015 12:00:00 AM","inTime":"Dec 31, 2015 2:53:41 PM","outTime":"Dec 31, 2015 3:43:47 PM","swipeEffectiveHours":3006000.0,"type":"PR"},{"userId":"50046","date":"Dec 31, 2015 12:00:00 AM","inTime":"Dec 31, 2015 5:16:24 PM","outTime":"Dec 31, 2015 6:01:33 PM","swipeEffectiveHours":2709000.0,"type":"PR"},{"userId":"50046","date":"Dec 31, 2015 12:00:00 AM","inTime":"Dec 31, 2015 6:05:50 PM","outTime":"Dec 31, 2015 6:20:43 PM","swipeEffectiveHours":893382.0,"type":"PR"}],"70053":[{"userId":"70053","date":"Dec 31, 2015 12:00:00 AM","inTime":"Dec 31, 2015 10:27:56 AM","outTime":"Dec 31, 2015 1:13:46 PM","swipeEffectiveHours":9950000.0,"type":"PR"},{"userId":"70053","date":"Dec 31, 2015 12:00:00 AM","inTime":"Dec 31, 2015 1:39:23 PM","outTime":"Dec 31, 2015 5:45:26 PM","swipeEffectiveHours":1.4763E7,"type":"PR"}],"60002":[{"userId":"60002","date":"Dec 31, 2015 12:00:00 AM","inTime":"Dec 31, 2015 9:39:51 AM","outTime":"Dec 31, 2015 1:03:18 PM","swipeEffectiveHours":1.2207E7,"type":"PR"},{"userId":"60002","date":"Dec 31, 2015 12:00:00 AM","inTime":"Dec 31, 2015 1:30:23 PM","outTime":"Dec 31, 2015 6:20:43 PM","swipeEffectiveHours":1.7420506E7,"type":"PR"}],"20068":[{"userId":"20068","date":"Dec 31, 2015 12:00:00 AM","inTime":"Dec 31, 2015 9:43:08 AM","outTime":"Dec 31, 2015 6:20:43 PM","swipeEffectiveHours":3.1055304E7,"type":"PR"}],"91468":[]},"usersList":[{"userId":"20068","name":"Dinesh Chandra Tewari","holidayId":2,"branch":"PUNE"},{"userId":"50046","name":"Shailendra Aragula","holidayId":1,"branch":"BANGALORE I"},{"userId":"60002","name":"Shashidhar N C","holidayId":1,"branch":"BANGALORE I"},{"userId":"60128","name":"Devarajan T L","holidayId":1,"branch":"BANGALORE I"},{"userId":"70008","name":"Sharmilla Myra Cordeiro","holidayId":1,"branch":"BANGALORE I"},{"userId":"70014","name":"P Ramesh Chandra","holidayId":1,"branch":"BANGALORE I"},{"userId":"70053","name":"Shobha K","holidayId":1,"branch":"BANGALORE I"},{"userId":"91468","name":"Sunand Kothila","holidayId":1,"branch":"BANGALORE I"},{"userId":"91780","name":"Krishnamurthy Udupa","holidayId":1,"branch":"BANGALORE I"}]}